MANIFEST.in
license.txt
readme.txt
setup.py
is_pal_vish/__init__.py
is_pal_vish.egg-info/PKG-INFO
is_pal_vish.egg-info/SOURCES.txt
is_pal_vish.egg-info/dependency_links.txt
is_pal_vish.egg-info/top_level.txt