Metadata-Version: 1.0
Name: is-pal-vish
Version: 0.0.1
Summary: palidrome checking function
Home-page: https://www.google.com/search?q=google&oq=google&aqs=chrome..69i57j35i39l2j0j69i60l2j69i65l2.3069j1j7&sourceid=chrome&ie=UTF-8
Author: vish
Author-email: UNKNOWN
License: MIT
Keywords: palindrome,python palindrome
Platform: UNKNOWN
